apb_timer/apb_timer.v
`timescale 1ns/1ps

module apb_timer #(
    parameter WIDTH = 8
)(
    input wire             PCLK,
    input wire             PRESETn,

    input wire             PSEL,
    input wire             PENABLE,
    input wire             PWRITE,
    input wire [7:0]       PADDR,
    input wire [31:0]      PWDATA,

    output reg [31:0]      PRDATA,
    output reg             timer_done
);

    // Register addresses
    localparam ADDR_LOAD    = 8'h00;
    localparam ADDR_CONTROL = 8'h04;
    localparam ADDR_STATUS  = 8'h08;
    localparam ADDR_COUNT   = 8'h0C;

    // Internal registers
    reg [WIDTH-1:0] load_val;
    reg [WIDTH-1:0] count;
    reg             running;

    // APB transfer detection
    wire apb_write;
    wire apb_read;

    assign apb_write = PSEL && PENABLE && PWRITE;
    assign apb_read  = PSEL && PENABLE && !PWRITE;

    // Timer and APB write logic
    always @(posedge PCLK or negedge PRESETn) begin

        if (!PRESETn) begin
            load_val   <= {WIDTH{1'b0}};
            count      <= {WIDTH{1'b0}};
            running    <= 1'b0;
            timer_done <= 1'b0;
        end

        else begin

            // APB write
            if (apb_write) begin

                case (PADDR)

                    // LOAD register
                    ADDR_LOAD: begin
                        load_val <= PWDATA[WIDTH-1:0];
                    end

                    // CONTROL register
                    // bit 0 = 1: Start
                    // bit 0 = 0: Stop
                    ADDR_CONTROL: begin

                        if (PWDATA[0]) begin
                            running    <= 1'b1;
                            count      <= load_val;
                            timer_done <= 1'b0;
                        end

                        else begin
                            running    <= 1'b0;
                            timer_done <= 1'b0;
                        end

                    end

                    default: begin
                    end

                endcase
            end

            // Timer countdown
            else if (running) begin

                if (count > 1) begin
                    count      <= count - 1'b1;
                    timer_done <= 1'b0;
                end

                else begin
                    count      <= {WIDTH{1'b0}};
                    running    <= 1'b0;
                    timer_done <= 1'b1;
                end

            end

            else begin
                timer_done <= 1'b0;
            end

        end
    end

    // APB read logic
    always @(*) begin

        PRDATA = 32'h00000000;

        if (apb_read) begin

            case (PADDR)

                // LOAD register
                ADDR_LOAD:
                    PRDATA = {{(32-WIDTH){1'b0}}, load_val};

                // CONTROL register
                ADDR_CONTROL:
                    PRDATA = {31'b0, running};

                // STATUS register
                ADDR_STATUS:
                    PRDATA = {31'b0, timer_done};

                // COUNT register
                ADDR_COUNT:
                    PRDATA = {{(32-WIDTH){1'b0}}, count};

                default:
                    PRDATA = 32'h00000000;

            endcase

        end
    end

    // Explicitly mark upper PWDATA bits as intentionally unused
    // when WIDTH = 8.
    wire [31:0] unused_PWDATA = PWDATA;

endmodule

apb_timer/apb_timer_tb.v
`timescale 1ns/1ps

module apb_timer_tb;

    // APB interface signals
    reg PCLK;
    reg PRESETn = 0;
    reg PSEL = 0;
    reg PENABLE = 0;
    reg PWRITE = 0;
    reg [7:0] PADDR = 0;
    reg [31:0] PWDATA = 0;

    wire [31:0] PRDATA;
    wire timer_done;

    // DUT instance
    apb_timer uut (
        .PCLK(PCLK),
        .PRESETn(PRESETn),
        .PSEL(PSEL),
        .PENABLE(PENABLE),
        .PWRITE(PWRITE),
        .PADDR(PADDR),
        .PWDATA(PWDATA),
        .PRDATA(PRDATA),
        .timer_done(timer_done)
    );

    // Clock generation
    initial PCLK = 0;
    always #5 PCLK <= ~PCLK;

    // Monitor timer completion
    always @(posedge timer_done)
        $display("Time=%0t : TIMER DONE", $time);

    // APB write task
    task apb_write(input [7:0] addr, input [31:0] data);
    begin
        @(posedge PCLK);

        PSEL    = 1;
        PWRITE  = 1;
        PENABLE = 0;
        PADDR   = addr;
        PWDATA  = data;

        @(posedge PCLK);

        PENABLE = 1;

        @(posedge PCLK);

        PSEL    = 0;
        PENABLE = 0;
        PWRITE  = 0;
    end
    endtask

    // APB read task
    task apb_read(input [7:0] addr);
    begin
        @(posedge PCLK);

        PSEL    = 1;
        PWRITE  = 0;
        PENABLE = 0;
        PADDR   = addr;

        @(posedge PCLK);

        PENABLE = 1;

        @(posedge PCLK);

        $display("Time=%0t : Read [0x%0h] = %0d",
                 $time, addr, PRDATA);

        PSEL    = 0;
        PENABLE = 0;
    end
    endtask

    // Test sequence
    initial begin

        // Create waveform
        $dumpfile("apb_timer.vcd");
        $dumpvars(0, apb_timer_tb);

        // Apply reset
        #10 PRESETn = 1;

        // Program load value = 5
        apb_write(8'h00, 32'd5);

        // Start timer
        apb_write(8'h04, 32'd1);

        // Wait and read status
        #80;
        apb_read(8'h08);

        // Program load value = 3
        apb_write(8'h00, 32'd3);

        // Start timer again
        apb_write(8'h04, 32'd1);

        // Read status
        #50;
        apb_read(8'h08);

        #50;

        $finish;

    end

endmodule

apb_timer/obj_dir/and_gate_dump.vcd
$version Generated by VerilatedVcd $end
$timescale 1ps $end

 $scope module TOP $end
  $scope module apb_timer_tb $end
   $var wire  8 ' PADDR [7:0] $end
   $var wire  1 - PCLK $end
   $var wire  1 % PENABLE $end
   $var wire 32 . PRDATA [31:0] $end
   $var wire  1 # PRESETn $end
   $var wire  1 $ PSEL $end
   $var wire 32 ( PWDATA [31:0] $end
   $var wire  1 & PWRITE $end
   $var wire  1 ) timer_done $end
   $scope module uut $end
    $var wire  8 3 ADDR_CONTROL [7:0] $end
    $var wire  8 5 ADDR_COUNT [7:0] $end
    $var wire  8 2 ADDR_LOAD [7:0] $end
    $var wire  8 4 ADDR_STATUS [7:0] $end
    $var wire  8 ' PADDR [7:0] $end
    $var wire  1 - PCLK $end
    $var wire  1 % PENABLE $end
    $var wire 32 . PRDATA [31:0] $end
    $var wire  1 # PRESETn $end
    $var wire  1 $ PSEL $end
    $var wire 32 ( PWDATA [31:0] $end
    $var wire  1 & PWRITE $end
    $var wire 32 1 WIDTH [31:0] $end
    $var wire  1 0 apb_read $end
    $var wire  1 / apb_write $end
    $var wire  8 + count [7:0] $end
    $var wire  8 * load_val [7:0] $end
    $var wire  1 , running $end
    $var wire  1 ) timer_done $end
    $var wire 32 ( unused_PWDATA [31:0] $end
   $upscope $end
  $upscope $end
 $upscope $end
$enddefinitions $end


#0
0#
0$
0%
0&
b00000000 '
b00000000000000000000000000000000 (
0)
b00000000 *
b00000000 +
0,
0-
b00000000000000000000000000000000 .
0/
00
b00000000000000000000000000001000 1
b00000000 2
b00000100 3
b00001000 4
b00001100 5
#5000
1-
#10000
1#
0-
#15000
1$
1&
b00000000000000000000000000000101 (
1-
#20000
0-
#25000
1%
b00000101 *
1-
1/
#30000
0-
#35000
0$
0%
0&
1-
0/
#40000
0-
#45000
1$
1&
b00000100 '
b00000000000000000000000000000001 (
1-
#50000
0-
#55000
1%
b00000101 +
1,
1-
1/
#60000
0-
#65000
0$
0%
0&
b00000100 +
1-
0/
#70000
0-
#75000
b00000011 +
1-
#80000
0-
#85000
b00000010 +
1-
#90000
0-
#95000
b00000001 +
1-
#100000
0-
#105000
1)
b00000000 +
0,
1-
#110000
0-
#115000
0)
1-
#120000
0-
#125000
1-
#130000
0-
#135000
1-
#140000
0-
#145000
1$
b00001000 '
1-
#150000
0-
#155000
1%
1-
10
#160000
0-
#165000
0$
0%
1-
00
#170000
0-
#175000
1$
1&
b00000000 '
b00000000000000000000000000000011 (
1-
#180000
0-
#185000
1%
b00000011 *
1-
1/
#190000
0-
#195000
0$
0%
0&
1-
0/
#200000
0-
#205000
1$
1&
b00000100 '
b00000000000000000000000000000001 (
1-
#210000
0-
#215000
1%
b00000011 +
1,
1-
1/
#220000
0-
#225000
0$
0%
0&
b00000010 +
1-
0/
#230000
0-
#235000
b00000001 +
1-
#240000
0-
#245000
1)
b00000000 +
0,
1-
#250000
0-
#255000
0)
1-
#260000
0-
#265000
1-
#270000
0-
#275000
1$
b00001000 '
1-
#280000
0-
#285000
1%
1-
10
#290000
0-
#295000
0$
0%
1-
00
